src/__init__.py
src/config.py
src/error_handling.py
src/messaging.py
src/security.py
src/server.py
src/tools.py
src/validation.py
loco_mcp_server-0.3.0.dist-info/METADATA
loco_mcp_server-0.3.0.dist-info/WHEEL
loco_mcp_server-0.3.0.dist-info/entry_points.txt
loco_mcp_server-0.3.0.dist-info/RECORD
